.gitignore
MANIFEST.in
README.rst
setup.cfg
setup.py
docs/HISTORY.txt
docs/LICENSE.GPL
docs/LICENSE.txt
docs/MANUAL.txt
raptus/__init__.py
raptus.article.listings.egg-info/PKG-INFO
raptus.article.listings.egg-info/SOURCES.txt
raptus.article.listings.egg-info/dependency_links.txt
raptus.article.listings.egg-info/entry_points.txt
raptus.article.listings.egg-info/namespace_packages.txt
raptus.article.listings.egg-info/not-zip-safe
raptus.article.listings.egg-info/requires.txt
raptus.article.listings.egg-info/top_level.txt
raptus/article/__init__.py
raptus/article/listings/__init__.py
raptus/article/listings/configure.zcml
raptus/article/listings/setuphandlers.py
raptus/article/listings/browser/__init__.py
raptus/article/listings/browser/configure.zcml
raptus/article/listings/browser/listing.pt
raptus/article/listings/browser/listing.py
raptus/article/listings/browser/listing_alternating.gif
raptus/article/listings/browser/listing_columns.gif
raptus/article/listings/browser/listing_left.gif
raptus/article/listings/browser/listing_right.gif
raptus/article/listings/i18n/raptus.article-de.mo
raptus/article/listings/i18n/raptus.article-de.po
raptus/article/listings/i18n/raptus.article-fr.mo
raptus/article/listings/i18n/raptus.article-fr.po
raptus/article/listings/i18n/raptus.article.pot
raptus/article/listings/profiles/default/cssregistry.xml
raptus/article/listings/profiles/default/import_steps.xml
raptus/article/listings/profiles/default/metadata.xml
raptus/article/listings/profiles/default/propertiestool.xml
raptus/article/listings/profiles/default/raptus.article.listings_install.txt
raptus/article/listings/profiles/default/skins.xml
raptus/article/listings/profiles/default/viewlets.xml
raptus/article/listings/skins/raptus_article_listings/raptus.article.listings.css.dtml
raptus/article/listings/upgrades/__init__.py
raptus/article/listings/upgrades/configure.zcml
raptus/article/listings/upgrades/profiles.zcml
raptus/article/listings/upgrades/profiles/10_to_11/propertiestool.xml