Metadata-Version: 1.1
Name: raptus.article.listings
Version: 2.0b9
Summary: Provides basic listing components which display articles contained in the article.
Home-page: https://github.com/Raptus/raptus.article.listings
Author: Raptus AG
Author-email: dev@raptus.com
License: GPL
Platform: UNKNOWN
Classifier: Programming Language :: Python
Classifier: Topic :: Software Development :: Libraries :: Python Modules
